{
  "version": "7",
  "dialect": "sqlite",
  "entries": [
    {
      "idx": 0,
      "version": "6",
      "when": 1775029952391,
      "tag": "0000_steady_phantom_reporter",
      "breakpoints": true
    },
    {
      "idx": 1,
      "version": "6",
      "when": 1776093831889,
      "tag": "0001_open_kabuki",
      "breakpoints": true
    },
    {
      "idx": 2,
      "version": "6",
      "when": 1776217895713,
      "tag": "0002_typical_magdalene",
      "breakpoints": true
    },
    {
      "idx": 3,
      "version": "6",
      "when": 1776567685888,
      "tag": "0003_add_rank_to_score_snapshots",
      "breakpoints": true
    },
    {
      "idx": 4,
      "version": "6",
      "when": 1776656703407,
      "tag": "0004_known_retro_girl",
      "breakpoints": true
    },
    {
      "idx": 5,
      "version": "6",
      "when": 1779338109644,
      "tag": "0005_security_hardening",
      "breakpoints": true
    }
  ]
}
